odoo/addons/ssi_outsource_work_rate/README.rst
odoo/addons/ssi_outsource_work_rate/__init__.py
odoo/addons/ssi_outsource_work_rate/__manifest__.py
odoo/addons/ssi_outsource_work_rate/data/approval_template_data.xml
odoo/addons/ssi_outsource_work_rate/data/ir_sequence_data.xml
odoo/addons/ssi_outsource_work_rate/data/policy_template_data.xml
odoo/addons/ssi_outsource_work_rate/data/sequence_template_data.xml
odoo/addons/ssi_outsource_work_rate/models/__init__.py
odoo/addons/ssi_outsource_work_rate/models/outsource_work_rate.py
odoo/addons/ssi_outsource_work_rate/models/outsource_work_rate_detail.py
odoo/addons/ssi_outsource_work_rate/security/ir.model.access.csv
odoo/addons/ssi_outsource_work_rate/security/ir_module_category_data.xml
odoo/addons/ssi_outsource_work_rate/security/ir_rule_data.xml
odoo/addons/ssi_outsource_work_rate/security/res_group_data.xml
odoo/addons/ssi_outsource_work_rate/static/description/icon.png
odoo/addons/ssi_outsource_work_rate/views/outsource_work_rate_view.xml
odoo14_addon_ssi_outsource_work_rate-14.0.1.1.0.dist-info/METADATA
odoo14_addon_ssi_outsource_work_rate-14.0.1.1.0.dist-info/WHEEL
odoo14_addon_ssi_outsource_work_rate-14.0.1.1.0.dist-info/top_level.txt
odoo14_addon_ssi_outsource_work_rate-14.0.1.1.0.dist-info/RECORD
